fuero/__init__.py
fuero/cli.py
fuero/core/__init__.py
fuero/core/ast_nodes.py
fuero/core/interpreter.py
fuero/core/lexer.py
fuero/core/parser.py
fuero/stdlib/__init__.py
fuero/stdlib/ai.py
fuero/stdlib/crypto.py
fuero/stdlib/database.py
fuero/stdlib/http.py
fuero/stdlib/json.py
fuero/stdlib/math.py
fuero/stdlib/string.py
fuero_lang-1.1.1.dist-info/licenses/LICENSE
fuero_lang-1.1.1.dist-info/METADATA
fuero_lang-1.1.1.dist-info/WHEEL
fuero_lang-1.1.1.dist-info/entry_points.txt
fuero_lang-1.1.1.dist-info/top_level.txt
fuero_lang-1.1.1.dist-info/RECORD
